build_backend.py
dsgrid/__init__.py
dsgrid/api/__init__.py
dsgrid/api/api_manager.py
dsgrid/api/app.py
dsgrid/api/models.py
dsgrid/api/response_models.py
dsgrid/apps/__init__.py
dsgrid/apps/project_viewer/app.py
dsgrid/apps/registration_gui.py
dsgrid/chronify.py
dsgrid/cli/__init__.py
dsgrid/cli/common.py
dsgrid/cli/config.py
dsgrid/cli/download.py
dsgrid/cli/dsgrid.py
dsgrid/cli/dsgrid_admin.py
dsgrid/cli/install_notebooks.py
dsgrid/cli/query.py
dsgrid/cli/registry.py
dsgrid/cloud/__init__.py
dsgrid/cloud/cloud_storage_interface.py
dsgrid/cloud/factory.py
dsgrid/cloud/fake_storage_interface.py
dsgrid/cloud/s3_storage_interface.py
dsgrid/common.py
dsgrid/config/__init__.py
dsgrid/config/annual_time_dimension_config.py
dsgrid/config/common.py
dsgrid/config/config_base.py
dsgrid/config/dataset_config.py
dsgrid/config/dataset_schema_handler_factory.py
dsgrid/config/date_time_dimension_config.py
dsgrid/config/dimension_config.py
dsgrid/config/dimension_config_factory.py
dsgrid/config/dimension_mapping_base.py
dsgrid/config/dimension_mappings_config.py
dsgrid/config/dimensions.py
dsgrid/config/dimensions_config.py
dsgrid/config/file_schema.py
dsgrid/config/index_time_dimension_config.py
dsgrid/config/input_dataset_requirements.py
dsgrid/config/mapping_tables.py
dsgrid/config/noop_time_dimension_config.py
dsgrid/config/project_config.py
dsgrid/config/registration_models.py
dsgrid/config/representative_period_time_dimension_config.py
dsgrid/config/simple_models.py
dsgrid/config/supplemental_dimension.py
dsgrid/config/time_dimension_base_config.py
dsgrid/data_models.py
dsgrid/dataset/__init__.py
dsgrid/dataset/dataset.py
dsgrid/dataset/dataset_expression_handler.py
dsgrid/dataset/dataset_mapping_manager.py
dsgrid/dataset/dataset_schema_handler_base.py
dsgrid/dataset/dataset_schema_handler_one_table.py
dsgrid/dataset/dataset_schema_handler_two_table.py
dsgrid/dataset/growth_rates.py
dsgrid/dataset/models.py
dsgrid/dataset/table_format_handler_base.py
dsgrid_toolkit-0.3.3.dist-info/METADATA
dsgrid_toolkit-0.3.3.dist-info/WHEEL
dsgrid_toolkit-0.3.3.dist-info/entry_points.txt
dsgrid_toolkit-0.3.3.dist-info/licenses/LICENSE
dsgrid_toolkit-0.3.3.dist-info/RECORD
