Metadata-Version: 2.4
Name: dsgrid-toolkit
Version: 0.3.3
Classifier: Development Status :: 3 - Alpha
Classifier: Intended Audience :: Science/Research
Classifier: License :: OSI Approved :: BSD License
Classifier: Natural Language :: English
Classifier: Programming Language :: Python :: 3.11
Requires-Dist: chronify~=0.6.0
Requires-Dist: click>=8.2,<9
Requires-Dist: dash
Requires-Dist: dash-bootstrap-components
Requires-Dist: duckdb>=1,<2
Requires-Dist: fastapi
Requires-Dist: json5
Requires-Dist: networkx
Requires-Dist: pandas
Requires-Dist: prettytable
Requires-Dist: pyarrow
Requires-Dist: pydantic~=2.11.6
Requires-Dist: requests
Requires-Dist: rich-click
Requires-Dist: semver
Requires-Dist: sqlalchemy>=2,<3
Requires-Dist: uvicorn
Requires-Dist: tzdata
Requires-Dist: httpx ; extra == 'dev'
Requires-Dist: pytest ; extra == 'dev'
Requires-Dist: pytest-cov ; extra == 'dev'
Requires-Dist: pre-commit ; extra == 'dev'
Requires-Dist: devtools ; extra == 'dev'
Requires-Dist: flake8 ; extra == 'dev'
Requires-Dist: mypy ; extra == 'dev'
Requires-Dist: pyarrow ; extra == 'dev'
Requires-Dist: maturin ; extra == 'dev'
Requires-Dist: furo ; extra == 'doc'
Requires-Dist: ghp-import ; extra == 'doc'
Requires-Dist: numpydoc ; extra == 'doc'
Requires-Dist: pandas-stubs ; extra == 'doc'
Requires-Dist: ruff ; extra == 'doc'
Requires-Dist: sphinx~=7.2 ; extra == 'doc'
Requires-Dist: sphinx-click~=5.0 ; extra == 'doc'
Requires-Dist: sphinx-copybutton~=0.5.2 ; extra == 'doc'
Requires-Dist: sphinx-tabs~=3.4 ; extra == 'doc'
Requires-Dist: sphinx-argparse~=0.4.0 ; extra == 'doc'
Requires-Dist: sphinxcontrib-programoutput ; extra == 'doc'
Requires-Dist: autodoc-pydantic[erdantic]~=2.0 ; extra == 'doc'
Requires-Dist: twine ; extra == 'release'
Requires-Dist: setuptools ; extra == 'release'
Requires-Dist: wheel ; extra == 'release'
Requires-Dist: chronify[spark] ; extra == 'spark'
Requires-Dist: pyspark==4.0.0 ; extra == 'spark'
Requires-Dist: thrift ; extra == 'spark'
Requires-Dist: thrift-sasl ; extra == 'spark'
Provides-Extra: dev
Provides-Extra: doc
Provides-Extra: release
Provides-Extra: spark
License-File: LICENSE
Summary: Python API for accessing demand-side grid model (dsgrid) datasets
Keywords: dsgrid
Author-email: Elaine Hale <elaine.hale@nrel.gov>, Lixi Liu <lixi.liu@nrel.gov>, Meghan Mooney <meghan.mooney@nrel.gov>, Daniel Thom <daniel.thom@nrel.gov>
Maintainer-email: Elaine Hale <elaine.hale@nrel.gov>
Requires-Python: >=3.11
Project-URL: Documentation, https://dsgrid.github.io/dsgrid/
Project-URL: GitHub, https://github.com/dsgrid/dsgrid
Project-URL: Homepage, https://www.nrel.gov/analysis/dsgrid
